Combinational Circuits/Mux/Nx1 Mux/mux_Nx1.v
module mux_Nx1 #(
    parameter N = 8,
    parameter WIDTH = 8
) (
    input  [N*WIDTH-1:0] in,
    input  [$clog2(N)-1:0] sel,
    output reg [WIDTH-1:0] out
);

always @(*) begin
    out = in[sel*WIDTH +: WIDTH];
end

endmodule

Combinational Circuits/Mux/Nx1 Mux/mux_Nx1_tb.v
`timescale 1ns / 1ns
`include "mux_Nx1.v"

module mux_Nx1_tb;

  parameter N = 8;
  parameter WIDTH = 8;
  localparam SEL_WIDTH = $clog2(N);

  reg [N*WIDTH-1:0] in;
  reg [SEL_WIDTH-1:0] sel;
  wire [WIDTH-1:0] out;

  // Instantiate the DUT
  mux_Nx1 #(
    .N(N),
    .WIDTH(WIDTH)
  ) uut (
    .in(in),
    .sel(sel),
    .out(out)
  );

  integer i;

  initial begin
    $dumpfile("mux_Nx1_tb.vcd");
    $dumpvars(1, mux_Nx1_tb);         
    $dumpvars(1, uut);               

    // Assign distinct values to all 8 inputs for clarity in waveform
    in[7*WIDTH +: WIDTH] = 8'hAA;
    in[6*WIDTH +: WIDTH] = 8'hBB;
    in[5*WIDTH +: WIDTH] = 8'hCC;
    in[4*WIDTH +: WIDTH] = 8'hDD;
    in[3*WIDTH +: WIDTH] = 8'h11;
    in[2*WIDTH +: WIDTH] = 8'h22;
    in[1*WIDTH +: WIDTH] = 8'h33;
    in[0*WIDTH +: WIDTH] = 8'h44;

    // Wait for GTKWave to load initial values
    #10;


    for (i = 0; i < N; i = i + 1) begin
      sel = i;
      #20; 
    end


    #20;

    $finish;
  end

endmodule

Combinational Circuits/Mux/Nx1 Mux/mux_Nx1_tb.vcd
$date
	Sat Aug 02 23:01:43 2025
$end
$version
	Icarus Verilog
$end
$timescale
	1ns
$end
$scope module mux_Nx1_tb $end
$var wire 8 ! out [7:0] $end
$var integer 32 " i [31:0] $end
$var reg 64 # in [63:0] $end
$var reg 3 $ sel [2:0] $end
$upscope $end
$scope module mux_Nx1_tb $end
$scope module uut $end
$var wire 64 % in [63:0] $end
$var wire 3 & sel [2:0] $end
$var reg 8 ' out [7:0] $end
$upscope $end
$upscope $end
$enddefinitions $end
#0
$dumpvars
bx '
bx &
b1010101010111011110011001101110100010001001000100011001101000100 %
bx $
b1010101010111011110011001101110100010001001000100011001101000100 #
bx "
bx !
$end
#10
b1000100 '
b1000100 !
b0 $
b0 &
b0 "
#30
b110011 '
b110011 !
b1 $
b1 &
b1 "
#50
b100010 '
b100010 !
b10 $
b10 &
b10 "
#70
b10001 '
b10001 !
b11 $
b11 &
b11 "
#90
b11011101 '
b11011101 !
b100 $
b100 &
b100 "
#110
b11001100 '
b11001100 !
b101 $
b101 &
b101 "
#130
b10111011 '
b10111011 !
b110 $
b110 &
b110 "
#150
b10101010 '
b10101010 !
b111 $
b111 &
b111 "
#170
b1000 "
